pv/__init__.py
pv/draw.py
pv/props.py
pv/types.py
pv/utils.py
piano_video-0.1.3.dist-info/METADATA
piano_video-0.1.3.dist-info/WHEEL
piano_video-0.1.3.dist-info/top_level.txt
piano_video-0.1.3.dist-info/RECORD
